Metadata-Version: 1.0
Name: k-ege
Version: 0.4
Summary: Gaussian and Binomial distributions
Home-page: UNKNOWN
Author: UNKNOWN
Author-email: stepan.kazancev.04@bk.ru
License: UNKNOWN
Platform: UNKNOWN
